bitflyer/__init__.py
bitflyer/bitflyer.py
bitflyer_py-0.0.5.dist-info/LICENSE
bitflyer_py-0.0.5.dist-info/METADATA
bitflyer_py-0.0.5.dist-info/WHEEL
bitflyer_py-0.0.5.dist-info/top_level.txt
bitflyer_py-0.0.5.dist-info/RECORD
