Metadata-Version: 2.1
Name: bitflyer-py
Version: 0.0.5
Summary: wrapper library for bitflyer api
Home-page: https://github.com/ti-ginkgo/bitflyer-python
Author: ishtos
Author-email: ginkgonut.9960@gmail.com
License: MIT
Keywords: bitflyer
Platform: UNKNOWN
Classifier: Programming Language :: Python
Requires-Dist: requests
